aegeantic-0.1.0.dist-info/licenses/LICENSE
agentic/__init__.py
agentic/agent.py
agentic/context.py
agentic/core.py
agentic/events.py
agentic/logging_util.py
agentic/logic.py
agentic/multi_agent.py
agentic/patterns.py
agentic/resilience.py
agentic/storage.py
agentic/tools.py
agentic/validation.py
aegeantic-0.1.0.dist-info/METADATA
aegeantic-0.1.0.dist-info/WHEEL
aegeantic-0.1.0.dist-info/top_level.txt
aegeantic-0.1.0.dist-info/RECORD
