Metadata-Version: 2.4
Name: aegeantic
Version: 0.1.0
Summary: A comprehensive LLM agent framework with streaming support, persistent context, and multi-agent orchestration
Author-email: Kuzey Akin <kuzeyakins1@gmail.com>
License-Expression: MIT
Project-URL: Homepage, https://github.com/LOGQS/agentic_framework
Project-URL: Documentation, https://github.com/LOGQS/agentic_framework#readme
Project-URL: Repository, https://github.com/LOGQS/agentic_framework
Project-URL: Issues, https://github.com/LOGQS/agentic_framework/issues
Keywords: llm,agent,ai,streaming,multi-agent,orchestration
Classifier: Development Status :: 3 - Alpha
Classifier: Intended Audience :: Developers
Classifier: Programming Language :: Python :: 3
Classifier: Programming Language :: Python :: 3.9
Classifier: Programming Language :: Python :: 3.10
Classifier: Programming Language :: Python :: 3.11
Classifier: Programming Language :: Python :: 3.12
Classifier: Topic :: Software Development :: Libraries :: Python Modules
Classifier: Topic :: Scientific/Engineering :: Artificial Intelligence
Requires-Python: >=3.9
License-File: LICENSE
Requires-Dist: rocksdict
Provides-Extra: dev
Requires-Dist: pytest>=7.0; extra == "dev"
Requires-Dist: pytest-asyncio>=0.21.0; extra == "dev"
Requires-Dist: pytest-cov>=4.0; extra == "dev"
Requires-Dist: pytest-timeout>=2.1; extra == "dev"
Requires-Dist: pytest-xdist>=3.0; extra == "dev"
Requires-Dist: coverage>=7.0; extra == "dev"
Requires-Dist: freezegun>=1.2; extra == "dev"
Requires-Dist: faker>=18.0; extra == "dev"
Dynamic: license-file
